{
  "castellano": [
    { 
      "datosPersonales":
        {
          "id":1,
          "titulo":"Datos Personales",
          "nombre":"Hernán Luis Veyret",
          "edad":"Edad: 44",
          "fechaNacimiento":"Fecha de Nacimiento:  08/10/1979",
          "dni":"DNI: 27688650",
          "nacionalidad": "Argentino",
          "estadoCivil":"Estado Civil: Casado",
          "hijos":"Hijos: 2",
          "direccion":"Direccion: America 617, San nicolas de los Arroyos, Bs.As. Argentina - (CP: 2900)",
          "whatsapp":"54+(11)-34025499",
          "email":"hernanveyret@hotmail.com",
          "instagram":"https://www.instagram.com/hernanveyret/",
          "linkedin":"https://www.linkedin.com/in/hernan-veyret-023252242/",
          "github":"https://github.com/hernanveyret?tab=repositories"
        }    
    },
    {
      "estudios":
      {
        "id":2,
        "titulo":"Estudios Cursados",
        "secundario":"Escuela Normal Superior Antonio Mentruit (ENSAM). Dirección: Manuel Castro 990, B1828CIB Banfield, Buenos Aires",
        "primario":"ESCUELA Nº 31 CARLOS GUIDO y SPANO, Dirección: Hipólito Yrigoyen 7672, B1832BQU Banfield, Buenos Aires Teléfono: 011 4242-0635",
        "tituloCursos":"Cursos",
        "cursohtmlycss":"Curso de HTML/CSS por Youtube de BloomIt Digital Academy. Duracion: 24hs",
        "cursojavascript":"Curso de JAVASCRIPT por Youtube de BloomIt Digital Academy. Duracion: 12:39Hs",
        "cursoreact":"Curso de React por Youtube de Jon Mircha. Duracion: 39:54hs",
        "cursogit":"Curso de Git / github por Youtube de Jon Mircha. Duracion: 5hs",
        "cursonotebook":"Reparador de Notebooks. CETAE Perú 263, C1067AAE CABA Tel: 011 5219-1233.",
        "cursoRv":"Introduccion basica a HTML/CSS/JAVASCRIPT por Revolucion Digital, Munisipalidad de San Nicolas De los Arroyos."
      }
    },
    {
      "idiomas":
      {
        "id":3,
        "titulo":"Idiomas",
        "idiomaUno":"Portuges abanzado"
      }
    },
    {
      "experienciaLaboral":[
       {
          "tituloSeccion": "Experiencia Labora",
          "titulo":"Castillos Inflables",
          "descripcion":"Alquiler de castillos inflables para eventos.",
          "fecha":"Actualidad."
       },
       {
        "titulo":"Calzados Lecika",
        "descripcion":"Puesto: Encargado, Dirección: Hipólito Irigoyen 2600 Capital federal, CP1090.eléfono: 011 49525177/2344 -Empleador  MALDJIAN VARTKES CUIT 23-18708324-9.",
        "fecha":"12/2007 - 07/2020"
      },
      {
        "titulo":"Cyber Tangara",
        "descripcion":"Puesto: Dueño, administración,  Atención al público,mantenimiento de computadoras. Cabo Frio - Rio de Janeiro - Brasil",
        "fecha":"12/2003 - 11/2007"
      },
      {
        "titulo":"Hotel Pousada Casa Do Catavento",
        "descripcion":"Barman, atencion al publico en recepcion. Dirección: R. G II, s/n - Lote 3 - Condominio Atlântico Praia de Fe-rradura, Búzios - RJ, 28950-000, Brasil -Teléfono: +55 222623-1141.",
        "fecha":"06/2003- 11/2003"
      },
      {
        "titulo":"HG Decoraciones",
        "descripcion":"Puesto: Colocacion de cortinas decorativas, ayudante de alfombrado y tapicería. Dirección: Anatole France 1900, Lanús Oeste, Buenos Aires Telefono:011 4241-9320 - Empleador GONZALEZ NOE JORGE ADRIAN - CUIT 30-69420764-9) ",
        "fecha":"08/1998 - 05/2003"
      },
      {
        "titulo":"OASIS - Tennis Club",
        "descripcion":"Encargado de mantenimiento de instalaciones, Canchas de tennis, paddle, papi futbol y mantenimiento y limpieza gral. Dirección: Alberto arroque 756, B1828HPO Banfield, Buenos Aires. Teléfono: 011 4288-2250 - Empleador CASANOVAS GUILLERMO LEONARDO CUIT 20-20617103-1",
        "fecha":"05/1996 - 07/1998"
      }
      ]
    },
    {
      "proyectos":[
        {
          "tituloProyecto":"Proyectos",
          "titulo":"ofertApp",
          "imagen":"",
          "url":"",
          "urlGit":"https://github.com/hernanveyret/webDeOfertas",
          "descripcion":""
        },
        {
          "titulo":"Lista de Tareas - React",
          "imagen":"",
          "url":"",
          "urlGit":"https://github.com/hernanveyret/toDoListReact",
          "descripcion":""
        },
        {
          "titulo":"Lista de Tareas - Js",
          "imagen":"",
          "url":"",
          "urlGit":"https://github.com/hernanveyret/toDoList",
          "descripcion":""
        },
        {
          "titulo":"Calzados Abi",
          "imagen":"",
          "url":"",
          "urlGit":"https://github.com/hernanveyret/calzadosabireact",
          "descripcion":""
        },
        {
          "titulo":"App del Tiempo",
          "imagen":"",
          "url":"",
          "urlGit":"https://github.com/hernanveyret/AppDelTiempo",
          "descripcion":""
        },
        {
          "titulo":"El ahorcado",
          "imagen":"",
          "url":"",
          "urlGit":"https://github.com/hernanveyret/el-ahorcado",
          "descripcion":""
        },
        {
          "titulo":"TA-TE-TI",
          "imagen":"",
          "url":"",
          "urlGit":"https://github.com/hernanveyret/TATETI-V3",
          "descripcion":""
        }
      ]
    }
  ],
  "ingles": [
    {
      "datosPersonales":
        {
          "id":1,
          "titulo":"Personal information",
          "nombre":"Veyret, Hernán Luis",
          "edad":"Age: 44",
          "fechaNacimiento":"Birthdate:  10/08/1979",
          "dni":"DNI: 27688650",
          "nacionalidad": "Argentino",
          "estadoCivil":"Civil status: Married",
          "hijos":"Children: 2",
          "direccion":"Address: America 617, San nicolas de los Arroyos, Bs.As. Argentina - (CP: 2900)",
          "whatsapp":"54+(11)-34025499",
          "email":"hernanveyret@hotmail.com",
          "instagram":"https://www.instagram.com/hernanveyret/",
          "linkedin":"https://www.linkedin.com/in/hernan-veyret-023252242/",
          "github":"https://github.com/hernanveyret?tab=repositories"
        }
    },
    {
      "estudios":
      {
        "id":2,
        "titulo":"Studies Completed",
        "secundario":"Escuela Normal Superior Antonio Mentruit (ENSAM). Address: Manuel Castro 990, B1828CIB Banfield, Buenos Aires",
        "primario":"ESCUELA Nº 31 CARLOS GUIDO y SPANO, Address: Hipólito Yrigoyen 7672, B1832BQU Banfield, Buenos Aires Teléfono: 011 4242-0635",
        "tituloCursos":"Courses",
        "cursohtmlycss":"HTML/CSS by BloomIt Digital Academy Youtube. Duration: 24 hours",
        "cursojavascript":"JAVASCRIPT by BloomIt Digital Academy Youtube. Duration: 12:39Hs",
        "cursoreact":"React on YouTube by Jon Mircha. Duration: 39:54 hours",
        "cursogit":"Git/github by Jon Mircha's Youtube. Duration: 5 hours",
        "cursonotebook":"Notebook Repairer. Address: CETAE Perú 263, C1067AAE CABA Tel: 011 5219-1233.",
        "cursoRv":"Basic introduction to HTML/CSS/JAVASCRIPT BY Revolucion Digital, Municipality of San Nicolas De los Arroyos."
      }
    },
    {
      "idiomas":
      {
        "id":3,
        "titulo":"Idiomas",
        "idiomaUno":"Portuges abanzado"
      }
    },
    {
      "experienciaLaboral":[
       {
          "tituloSeccion": "Work experience",
          "titulo":"Inflatable castles",
          "descripcion":"Inflatable castle rental for events.",
          "fecha":"Present."
       },
       {
        "titulo":"Calzados Lecika",
        "descripcion":"Position: Manager, Address: Hipólito Irigoyen 2600 Capital federal, CP1090. Phone: 011 49525177/2344 - Employer MALDJIAN VARTKES CUIT 23-18708324-9.",
        "fecha":"12/2007 - 07/2020"
      },
      {
        "titulo":"Cyber Tangara",
        "descripcion":"Position: Owner, administration, customer service, computer maintenance. Cabo Frio - Rio de Janeiro - Brasil",
        "fecha":"12/2003 - 11/2007"
      },
      {
        "titulo":"Hotel Pousada Casa Do Catavento",
        "descripcion":"Barman, atencion al publico en recepcion. Dirección: R. G II, s/n - Lote 3 - Condominio Atlântico Praia de Fe-rradura, Búzios - RJ, 28950-000, Brasil -Teléfono: +55 222623-1141.",
        "fecha":"06/2003- 11/2003"
      },
      {
        "titulo":"HG Decoraciones",
        "descripcion":"Puesto: Colocacion de cortinas decorativas, ayudante de alfombrado y tapicería. Dirección: Anatole France 1900, Lanús Oeste, Buenos Aires Telefono:011 4241-9320 - Empleador GONZALEZ NOE JORGE ADRIAN - CUIT 30-69420764-9) ",
        "fecha":"08/1998 - 05/2003"
      },
      {
        "titulo":"OASIS - Tennis Club",
        "descripcion":"Encargado de mantenimiento de instalaciones, Canchas de tennis, paddle, papi futbol y mantenimiento y limpieza gral. Dirección: Alberto arroque 756, B1828HPO Banfield, Buenos Aires. Teléfono: 011 4288-2250 - Empleador CASANOVAS GUILLERMO LEONARDO CUIT 20-20617103-1",
        "fecha":"05/1996 - 07/1998"
      }
      ]
    }
  ]
}